{
  "type": "minecraft:entity",
  "pools": [
    {
      "rolls": 1,
      "entries": [
        {
          "type": "minecraft:item",
		  "name": "minecraft:structure_block",
          "functions": [
            {
			  "function": "minecraft:set_name",
			  "name": {"translate":"mech.rod.diamond","color":"dark_aqua","italic":false}
			},
			{
			  "function": "minecraft:set_lore",
			  "lore": [
				 {"translate":"mech.lore.upgrade_energy_saber","color":"gray","italic":false},
				[{"translate":"mech.lore.upgrade_effects","color":"gray","italic":false},{"text":" "},{"translate":"mech.lore.upgrade_reinforced"}],
				{"translate":"mech.lore.added_by","color":"blue","italic":false}
			  ]
			},
			{
              "function": "minecraft:set_nbt",
              "tag":"{CustomModelData: 6421512, HideFlags: 32, mechanization:{ id:\"diamond_rod\", modular_upgrade:{type:1b, effect:\"reinforced\", max_durability:1500, base_stats:{}, bonus_stats:{}} }, smithed:{ dict:{rod:{diamond:1b}} }}"
            }
          ]
        }
      ]
    }
  ]
}