{
  "pattern": [
    "  IGI    ",
    "  CMC  R ",
    "  IFI    "
  ],
  "key": {
    "I": {
      "type" : "smithed:item_entry",
      "id" : "minecraft:iron_ingot"
    },
    "F": {
      "type" : "smithed:item_entry",
      "id" : "minecraft:blast_furnace"
    },
    "G": {
      "type" : "smithed:datapack_item_entry",
      "id" : "mechanization:base_resources/gold_gear"
    },
    "C": {
      "type" : "smithed:datapack_item_entry",
      "id" : "mechanization:base_resources/copper_rod"
    },
    "M": {
      "type" : "smithed:datapack_item_entry",
      "id" : "mechanization:base/tier1_machine_frame"
    },
    "R": {
      "type" : "smithed:datapack_item_entry",
      "id" : "mechanization:machines/electric_furnace"
    }
  },
  "result": {
    "type" : "smithed:datapack_item_entry",
    "id" : "mechanization:machines/electric_furnace"
  },
  "category": "mechanization:machine_crafting_table"
}