{
  "pattern": [
    "1  ",
    "  2",
    "   "
  ],
  "key": {
    "1": {
      "type": "smithed:item_list",
      "items": [
        {
          "type": "smithed:item_entry",
          "id": "minecraft:coal_ore"
        },
        {
          "type": "smithed:item_entry",
          "id": "minecraft:deepslate_coal_ore"
        }
      ]
    },
    "2": {
      "type": "smithed:item_entry",
      "id": "minecraft:coal"
    }
  },
  "result": {
      "type": "smithed:item_entry",
      "id": "minecraft:coal"
  },
  "category": "mechanization:grinder"
}