{
    "display": {
        "title": {
            "translate": "mech.advancements.machines.machine_frame_2.title"
        },
        "description": {
            "translate": "mech.advancements.machines.machine_frame_2.description"
        },
        "icon": {
            "item": "minecraft:diamond_shovel",
            "nbt": "{Damage:80,Unbreakable:1b}"
        },
        "frame": "goal"
    },
    "criteria": {
        "have_frame_2": {
            "trigger": "minecraft:inventory_changed",
            "conditions": {
                "items": [{
                        "nbt": "{mech_itemid:2201}"
                    }
                ]
            }
        }
    },
    "parent": "mechanization:machines\/alloy_furnace"
}
